elk_mq.cp310-win_amd64.pyd
event_queue/service_event.rs
elk_mq-0.1.1.dist-info/LICENSE
elk_mq-0.1.1.dist-info/METADATA
elk_mq-0.1.1.dist-info/WHEEL
elk_mq-0.1.1.dist-info/top_level.txt
elk_mq-0.1.1.dist-info/RECORD
