Metadata-Version: 2.1
Name: elk-mq
Version: 0.1.1
Summary: A Message Queue implementation in rust, available as a python extension module
Author-email: Tijmen Verhoef <tijmenmenno@gmail.com>
License: Apache-2.0
Project-URL: repository, https://github.com/nemjit001/elk-mq
Project-URL: homepage, https://github.com/nemjit001/elk-mq
Classifier: Programming Language :: Python :: 3
Classifier: Programming Language :: Rust
Classifier: Programming Language :: Python :: Implementation :: CPython
Classifier: License :: OSI Approved :: Apache Software License
Requires-Python: >=3
License-File: LICENSE
